pynums/Closeness.py
pynums/Prime.py
pynums/__init__.py
pynums/core.py
pynums/digits.py
pynums/hard_math.py
pynums/machine_computing.py
pynums/ratio.py
pynums/rest/Checking.py
pynums/rest/__init__.py
pynums/rest/rest_func.py
pynums/rest/statistics.py
pynums-1.1.0.dist-info/licenses/LICENSE
pynums-1.1.0.dist-info/METADATA
pynums-1.1.0.dist-info/WHEEL
pynums-1.1.0.dist-info/top_level.txt
pynums-1.1.0.dist-info/RECORD
