Metadata-Version: 2.4
Name: pynums
Version: 1.1.0
Summary: A simple library for python made by Andriy Zhuk
Home-page: https://github.com/azuk13215/pynumspi
Author: Andriy Zhuk
Author-email: azuk37712@gmail.com
License: MIT
Classifier: Programming Language :: Python :: 3
Classifier: License :: OSI Approved :: MIT License
Classifier: Operating System :: OS Independent
License-File: LICENSE
Dynamic: license-file
